HISTORY.rst
LICENSE
MANIFEST.in
README.rst
setup.py
scripts/sushi
sushi/__init__.py
sushi/cli.py
sushi/conf.py
sushi/cookbook.py
sushi/core.py
sushi/env.py
sushi/exceptions.py
sushi/logger.py
sushi/recipes.py
sushi/starter.py
sushi/tools.py
sushi/unbundler.py
sushi.egg-info/PKG-INFO
sushi.egg-info/SOURCES.txt
sushi.egg-info/dependency_links.txt
sushi.egg-info/requires.txt
sushi.egg-info/top_level.txt