Metadata-Version: 1.1
Name: sushi
Version: 0.3.7
Summary: Create package template for everything
Home-page: https://github.com/toxinu/sushi/
Author: toxinu
Author-email: toxinu@gmail.com
License: Sushi
